object_storage_proxy-0.4.3.dist-info/METADATA
object_storage_proxy-0.4.3.dist-info/WHEEL
object_storage_proxy-0.4.3.dist-info/licenses/LICENSE
object_storage_proxy.libs/libcom_err-2abe824b.so.2
object_storage_proxy.libs/libcrypto-d3570994.so.10
object_storage_proxy.libs/libgssapi_krb5-497db0c6.so.2
object_storage_proxy.libs/libk5crypto-b1f99d5c.so.3
object_storage_proxy.libs/libkeyutils-dfe70bd6.so.1
object_storage_proxy.libs/libkrb5-fcafa220.so.3
object_storage_proxy.libs/libkrb5support-d0bcff84.so.0
object_storage_proxy.libs/libpcre-9513aab5.so.1
object_storage_proxy.libs/libselinux-0922c95c.so.1
object_storage_proxy.libs/libssl-cd1d6220.so.10
object_storage_proxy/__init__.py
object_storage_proxy/object_storage_proxy.pypy310-pp73-x86_64-linux-gnu.so
object_storage_proxy-0.4.3.dist-info/RECORD
