Metadata-Version: 2.4
Name: object-storage-proxy
Version: 0.4.3
Classifier: License :: Other/Proprietary License
Classifier: Programming Language :: Rust
Classifier: Programming Language :: Python :: Implementation :: CPython
Classifier: Programming Language :: Python :: Implementation :: PyPy
Requires-Dist: python-dotenv>=1.1.0
Requires-Dist: patchelf>=0.17.2.2 ; sys_platform == 'linux'
License-File: LICENSE
Summary: <object-storage-proxy ⚡> Yet Another Object Storage Proxy
Author-email: Jeroen <jeroen@flexworks.eu>
Requires-Python: >=3.10
Project-URL: Homepage, https://osp.flexworks.eu
Project-URL: Documentation, https://osp.flexworks.eu
Project-URL: Repository, https://github.com/opensourceworks-org/object-storage-proxy/tree/main
Project-URL: BugTracker, https://github.com/opensourceworks-org/object-storage-proxy/issues
